swift_actor_critic/__init__.py
swift_actor_critic/cpp/__init__.py
swift_actor_critic-0.1.4.dist-info/METADATA
swift_actor_critic-0.1.4.dist-info/WHEEL
swift_actor_critic-0.1.4.dist-info/top_level.txt
swift_actor_critic-0.1.4.dist-info/RECORD
