Metadata-Version: 2.4
Name: swift-actor-critic
Version: 0.1.4
Summary: Python bindings for Swift Actor-Critic algorithm
Author-email: Khurram Javed <kjaved@example.com>
License: MIT
Project-URL: Homepage, https://github.com/kjaved0/swift-actor-critic
Project-URL: Repository, https://github.com/kjaved0/swift-actor-critic
Classifier: Programming Language :: Python :: 3
Classifier: Programming Language :: Python :: 3.7
Classifier: Programming Language :: Python :: 3.8
Classifier: Programming Language :: Python :: 3.9
Classifier: Programming Language :: Python :: 3.10
Classifier: Programming Language :: Python :: 3.11
Classifier: Programming Language :: Python :: 3.12
Classifier: Operating System :: OS Independent
Requires-Python: >=3.7
